castAway/__main__.py
castAway/cli.py
castAway/core.py
castAway/db.py
castAway/player.py
castAway/screen.py
castAway/test.py
castaway_cli-0.0.4.dist-info/METADATA
castaway_cli-0.0.4.dist-info/WHEEL
castaway_cli-0.0.4.dist-info/entry_points.txt
castaway_cli-0.0.4.dist-info/top_level.txt
castaway_cli-0.0.4.dist-info/RECORD
