Metadata-Version: 2.4
Name: castaway-cli
Version: 0.0.4
Summary: Minimalist TUI Podcast Client for Hackers, Cast-Away is a lightweight, keyboard-driven terminal application designed for developers who want to listen to podcasts without leaving their terminal environment. Built with Python and Textual, it provides a distraction-free experience with real-time audio visualization.
Author-email: madushnaka rajapakshe <MadushankaRajapaksha999@gmail.com>
License: MIT
Project-URL: Homepage, https://github.com/MadushankaRajapaksha/castAway
Project-URL: Bug Tracker, https://github.com/MadushankaRajapaksha/castAway/issues
Classifier: Programming Language :: Python :: 3
Classifier: License :: OSI Approved :: MIT License
Classifier: Operating System :: OS Independent
Requires-Python: >=3.8
Requires-Dist: rich>=10.0.0
Requires-Dist: typer>=0.9.0
Requires-Dist: textual>=0.1.0
Requires-Dist: feedparser>=6.0.0
Requires-Dist: requests>=2.0.0
